odoo10_addon_mass_mailing_resend-10.0.1.0.0-py2.7-nspkg.pth
odoo/addons/mass_mailing_resend/README.rst
odoo/addons/mass_mailing_resend/__init__.py
odoo/addons/mass_mailing_resend/__manifest__.py
odoo/addons/mass_mailing_resend/i18n/es.po
odoo/addons/mass_mailing_resend/models/__init__.py
odoo/addons/mass_mailing_resend/models/mass_mailing.py
odoo/addons/mass_mailing_resend/static/description/icon.png
odoo/addons/mass_mailing_resend/static/description/icon.svg
odoo/addons/mass_mailing_resend/tests/__init__.py
odoo/addons/mass_mailing_resend/tests/test_mass_mailing_resend.py
odoo/addons/mass_mailing_resend/views/mass_mailing_views.xml
odoo10_addon_mass_mailing_resend-10.0.1.0.0.dist-info/DESCRIPTION.rst
odoo10_addon_mass_mailing_resend-10.0.1.0.0.dist-info/METADATA
odoo10_addon_mass_mailing_resend-10.0.1.0.0.dist-info/RECORD
odoo10_addon_mass_mailing_resend-10.0.1.0.0.dist-info/WHEEL
odoo10_addon_mass_mailing_resend-10.0.1.0.0.dist-info/metadata.json
odoo10_addon_mass_mailing_resend-10.0.1.0.0.dist-info/namespace_packages.txt
odoo10_addon_mass_mailing_resend-10.0.1.0.0.dist-info/top_level.txt
